a2a_redis/__init__.py
a2a_redis/event_queue_protocol.py
a2a_redis/pubsub_queue.py
a2a_redis/pubsub_queue_manager.py
a2a_redis/push_notification_config_store.py
a2a_redis/queue_types.py
a2a_redis/streams_consumer_strategy.py
a2a_redis/streams_queue.py
a2a_redis/streams_queue_manager.py
a2a_redis/task_store.py
a2a_redis/utils.py
a2a_redis-0.1.1.dist-info/METADATA
a2a_redis-0.1.1.dist-info/WHEEL
a2a_redis-0.1.1.dist-info/top_level.txt
a2a_redis-0.1.1.dist-info/RECORD
