Metadata-Version: 2.4
Name: a2a-redis
Version: 0.1.1
Summary: Redis components for the Agent-to-Agent (A2A) Python SDK
Author: Redis, Inc., Andrew Brookins
License: MIT
Project-URL: Homepage, https://github.com/redis-developer/a2a-redis
Project-URL: Repository, https://github.com/redis-developer/a2a-redis
Project-URL: Issues, https://github.com/redis-developer/a2a-redis/issues
Keywords: a2a,agent,redis,queue,task-store
Classifier: Development Status :: 4 - Beta
Classifier: Intended Audience :: Developers
Classifier: License :: OSI Approved :: MIT License
Classifier: Operating System :: OS Independent
Classifier: Programming Language :: Python :: 3
Classifier: Programming Language :: Python :: 3.11
Classifier: Programming Language :: Python :: 3.12
Classifier: Topic :: Software Development :: Libraries :: Python Modules
Classifier: Topic :: System :: Distributed Computing
Requires-Python: >=3.11
Requires-Dist: redis>=4.0.0
Requires-Dist: a2a-sdk>=0.2.16
Requires-Dist: uvicorn>=0.35.0
Provides-Extra: dev
Requires-Dist: pytest>=6.0; extra == "dev"
Requires-Dist: pytest-asyncio; extra == "dev"
Requires-Dist: pytest-cov; extra == "dev"
Requires-Dist: black; extra == "dev"
Requires-Dist: isort; extra == "dev"
Requires-Dist: mypy; extra == "dev"
Requires-Dist: ruff; extra == "dev"
